[IF standalone]
[ZONE WGCAL:WGCAL_HTMLHEAD]
<table width="100%" class="wToolButtonUnselect" cellspacing="0" cellpadding="0"><tr><td>[TEXT:search result]</td></tr></tr></table>
[ENDIF standalone]

[IF noresult]<div width="100%" class="WEvDays">[TEXT:no event]</div>[ENDIF noresult]
[BLOCK btime]<div class="WEvDays" style="padding:2px" onmouseover="closeMenu('calpopup');">[date]
<table width="100%" cellspacing="0">
[BLOCK devents[date]]<tr valign="top" class="WEvDefault" onmouseover="this.className='WEvOver'" onclick="subwindow(400, 650, 'ViewEvent[id]', '[CORE_STANDURL]&app=[IF edit]GENERIC&action=GENERIC_EDIT[ENDIF edit][IFNOT edit]FDL&action=IMPCARD[ENDIF edit]&id=[id]');" onmouseout="this.className='WEvDefault'">
<td onContextMenu="SetCurrentEvent([id], '[TSSTART]'); openMenu(event,'calpopup',[RG]);return false" onMouseDown="if (shiftKeyPushed(event)) { SetCurrentEvent([id], '[TSSTART]');openMenu(event,'calpopup',[RG])}">[EvCard]</td>
</tr>[ENDBLOCK devents[date]]</table></div>[ENDBLOCK btime]

[ZONE WGCAL:WGCAL_POPUP]

[IF standalone][ZONE WGCAL:WGCAL_HTMLFOOT][ENDIF standalone]
