
<script>document.needreload=true;</script>
[ZONE FDL:VIEWFRAME?frameid=FR_BASIC]


<table style="width:100%;border:1px solid"><tr><td style="width:33%">[V_BOOK_HEADLEFT]</td><td style="width:33%;text-align:center">[V_BOOK_HEADMIDDLE]</td><td style="text-align:right">[V_BOOK_HEADRIGHT]</td></tr></table>
<div style="text-align:center">
<ul>
[BLOCK CHAPTERS]
<li style="list-style-type:none;margin-left:[level]px"><a class="tooltip" title="[chap_comment]" href="[CORE_STANDURL]app=FDL&action=FDL_CARD&id=[id]">[chap_level] [chap_title]</a></li>
[ENDBLOCK CHAPTERS]
</ul>
</div><table style="width:100%;border:1px solid"><tr><td style="width:33%">[V_BOOK_FOOTLEFT]</td><td style="width:33%;text-align:center">[V_BOOK_FOOTMIDDLE]</td><td style="text-align:right">[V_BOOK_FOOTRIGHT]</td></tr></table>
